xgdatatools/__init__.py
xgdatatools/extractxgdata.py
xgdatatools/xgimport.py
xgdatatools/xgstruct.py
xgdatatools/xgutils.py
xgdatatools/xgzarc.py
xgdatatools-0.0.1.dist-info/METADATA
xgdatatools-0.0.1.dist-info/WHEEL
xgdatatools-0.0.1.dist-info/licenses/LICENSE.txt
xgdatatools-0.0.1.dist-info/RECORD
